README.rst
setup.py
PyBM.egg-info/PKG-INFO
PyBM.egg-info/SOURCES.txt
PyBM.egg-info/dependency_links.txt
PyBM.egg-info/requires.txt
PyBM.egg-info/top_level.txt
pybm/HttpClient.py
pybm/JenkinsMonitor.py
pybm/Job.py
pybm/MockMonitor.py
pybm/ProgressBar.py
pybm/__init__.py
pybm/logging.conf
pybm/pyBM.py
pybm/segoeui.ttf
pybm/util.py
pybm/../LICENSE
pybm/../NOTICE
scripts/pybm