Metadata-Version: 1.0
Name: PyBM
Version: 0.0.11
Summary: Python Build Monitor
Home-page: http://www.circuitdb.com/pybm/
Author: Jos Hendriks
Author-email: UNKNOWN
License: UNKNOWN
Platform: UNKNOWN
